topovelo/__init__.py
topovelo/plotting.py
topovelo/preprocessing.py
topovelo/analysis/__init__.py
topovelo/analysis/evaluation.py
topovelo/analysis/evaluation_util.py
topovelo/analysis/perf_logger.py
topovelo/analysis/plot_config.py
topovelo/analysis/velocity_util.py
topovelo/model/__init__.py
topovelo/model/model_profiler.py
topovelo/model/model_util.py
topovelo/model/scvelo_util.py
topovelo/model/training_data.py
topovelo/model/vae.py
topovelo/model/vanilla_vae.py
topovelo/model/velocity.py
topovelo/scvelo_preprocessing/__init__.py
topovelo/scvelo_preprocessing/logging.py
topovelo/scvelo_preprocessing/moments.py
topovelo/scvelo_preprocessing/neighbors.py
topovelo/scvelo_preprocessing/settings.py
topovelo/scvelo_preprocessing/utils.py
topovelo/simulation/__init__.py
topovelo/simulation/rna.py
topovelo/simulation/sim_data.py
topovelo/simulation/spatial.py
topovelo/simulation/utils.py
topovelo-0.0.2.dist-info/LICENSE
topovelo-0.0.2.dist-info/METADATA
topovelo-0.0.2.dist-info/WHEEL
topovelo-0.0.2.dist-info/top_level.txt
topovelo-0.0.2.dist-info/RECORD
